hello_sdk/__init__.py
hello_sdk/hello.py
hello_sdk/sdk.py
hello_sdk_demo-0.0.2.dist-info/METADATA
hello_sdk_demo-0.0.2.dist-info/WHEEL
hello_sdk_demo-0.0.2.dist-info/top_level.txt
hello_sdk_demo-0.0.2.dist-info/RECORD
