Metadata-Version: 2.4
Name: hello-sdk-demo
Version: 0.0.2
Summary: A minimal example Python SDK
Author: Your Name
Author-email: you@example.com
Requires-Python: >=3.6
Dynamic: author
Dynamic: author-email
Dynamic: description
Dynamic: description-content-type
Dynamic: requires-python
Dynamic: summary
